{
  "version": "3.1.0",
  "timestamp": "2026-01-03T22:15:05.512Z",
  "buildNumber": 174,
  "changelog": [
    {
      "version": "3.1.0",
      "date": "2026-01-03",
      "type": "minor",
      "changes": [
        "feat: Enhance fullscreen support for iOS with CSS fallback and exit button",
        "🔖 Bump version to 3.0.0 [skip-version]"
      ]
    },
    {
      "version": "3.0.0",
      "date": "2026-01-03",
      "type": "major",
      "changes": [
        "breaking!:modify get_by_user , Implement Infinite Scroll Manager and Wallet Stats Renderer",
        "🔖 Bump version to 2.20.0 [skip-version]"
      ]
    },
    {
      "version": "2.20.0",
      "date": "2026-01-03",
      "type": "minor",
      "changes": [
        "feat: Update quest tracking logic to use configurable score thresholds and add production fix script for quest data",
        "🔖 Bump version to 2.19.0 [skip-version]"
      ]
    },
    {
      "version": "2.19.0",
      "date": "2026-01-03",
      "type": "minor",
      "changes": [
        "feat: Improve cumulative data initialization for quest tracking and add script to fix existing data",
        "🔖 Bump version to 2.18.0 [skip-version]"
      ]
    },
    {
      "version": "2.18.0",
      "date": "2026-01-03",
      "type": "minor",
      "changes": [
        "feat: Update quest progress handling and add consistency fixer script",
        "🔖 Bump version to 2.17.0 [skip-version]"
      ]
    },
    {
      "version": "2.17.0",
      "date": "2026-01-03",
      "type": "minor",
      "changes": [
        "feat: Add daily quest reset scheduler for automatic quest management",
        "🔖 Bump version to 2.16.1 [skip-version]"
      ]
    },
    {
      "version": "2.16.1",
      "date": "2026-01-02",
      "type": "patch",
      "changes": [
        "style: Remove animations from reward icons in level widget and quest hero styles",
        "🔖 Bump version to 2.16.0 [skip-version]"
      ]
    },
    {
      "version": "2.16.0",
      "date": "2026-01-02",
      "type": "minor",
      "changes": [
        "feat: Implement Rainbow Rush daily quests setup and processing logic",
        "🔖 Bump version to 2.15.0 [skip-version]"
      ]
    },
    {
      "version": "2.15.0",
      "date": "2026-01-02",
      "type": "minor",
      "changes": [
        "feat: Add Merge Tower Defense daily quests and processing logic in QuestTracker",
        "🔖 Bump version to 2.14.0 [skip-version]"
      ]
    },
    {
      "version": "2.14.0",
      "date": "2026-01-02",
      "type": "minor",
      "changes": [
        "feat: Implement daily reset functionality for Seven and Yatzi quests, including quest tracking and UI updates",
        "🔖 Bump version to 2.13.2 [skip-version]"
      ]
    }
  ]
}
