{
  "version": "1.11.1",
  "timestamp": "2025-12-08T16:42:20.108Z",
  "buildNumber": 27,
  "changelog": [
    {
      "version": "1.11.1",
      "date": "2025-12-08",
      "type": "patch",
      "changes": [
        "fix: [RAINBOW RUSH] Update stats display by removing high score from game over screen",
        "🔖 Bump version to 1.11.0 [skip-version]"
      ]
    },
    {
      "version": "1.11.0",
      "date": "2025-12-08",
      "type": "minor",
      "changes": [
        "feat:[RAINBOW RUSH] Integrate backend leaderboard for high score management and update menu interactions",
        "🔖 Bump version to 1.10.1 [skip-version]"
      ]
    },
    {
      "version": "1.10.1",
      "date": "2025-12-08",
      "type": "patch",
      "changes": [
        "fix: Update leaderboard rendering to conditionally display rewards and adjust layout for better UX",
        "🔖 Bump version to 1.10.0 [skip-version]"
      ]
    },
    {
      "version": "1.10.0",
      "date": "2025-12-08",
      "type": "minor",
      "changes": [
        "feat:[RAINBOW RUSH] Implement background rendering system with layered and particle renderers",
        "🔖 Bump version to 1.9.0 [skip-version]"
      ]
    },
    {
      "version": "1.9.0",
      "date": "2025-12-07",
      "type": "minor",
      "changes": [
        "fix: Enhance tower upgrade logic with error logging and improve button styles; update scrollbar styles for better UX",
        "feat: Enhance logging configuration, improve leaderboard and profile styles, and update wallet widget UI",
        "🔖 Bump version to 1.8.6 [skip-version]"
      ]
    },
    {
      "version": "1.8.6",
      "date": "2025-12-07",
      "type": "patch",
      "changes": [
        "fix: Update scrollbar colors for Webkit browsers and refine Firefox scrollbar styles",
        "🔖 Bump version to 1.8.5 [skip-version]"
      ]
    },
    {
      "version": "1.8.5",
      "date": "2025-12-07",
      "type": "patch",
      "changes": [
        "fix: Update scrollbar styles for Webkit browsers and improve CSS caching strategy in nginx configuration",
        "🔖 Bump version to 1.8.4 [skip-version]"
      ]
    },
    {
      "version": "1.8.4",
      "date": "2025-12-07",
      "type": "patch",
      "changes": [
        "fix: Add custom scrollbar styles for Webkit and Firefox browsers",
        "🔖 Bump version to 1.8.3 [skip-version]"
      ]
    },
    {
      "version": "1.8.3",
      "date": "2025-12-07",
      "type": "patch",
      "changes": [
        "Merge branch 'master' of https://github.com/davvoz/Ggameplatform",
        "fix: [ TOWER DEFENSE ] Enhance tower upgrade logic with error logging and improve button styles",
        "🔖 Bump version to 1.8.2 [skip-version]"
      ]
    },
    {
      "version": "1.8.2",
      "date": "2025-12-07",
      "type": "patch",
      "changes": [
        "fix: Update countdown timer logic to calculate days until next reset on Monday",
        "🔖 Bump version to 1.8.1 [skip-version]"
      ]
    }
  ]
}
